attlesnake/__init__.py
attlesnake/util.py
attlesnake/parameter/__init__.py
attlesnake/parameter/base.py
attlesnake/parameter/constants.py
attlesnake/parameter/direction_cosine_matrix.py
attlesnake/parameter/euler_angle.py
attlesnake/parameter/principal_rotation_vector.py
attlesnake/parameter/quaternion.py
attlesnake/parameter/rodrigues.py
attlesnake-0.2.0.dist-info/LICENSE
attlesnake-0.2.0.dist-info/METADATA
attlesnake-0.2.0.dist-info/WHEEL
attlesnake-0.2.0.dist-info/top_level.txt
attlesnake-0.2.0.dist-info/RECORD
