Metadata-Version: 2.1
Name: attlesnake
Version: 0.2.0
Summary: Attitude dynamics in Python
Home-page: https://github.com/mdbernard/attlesnake
Author: Mike Bernard
Author-email: mdbernard@protonmail.com
License: UNKNOWN
Project-URL: Bug Tracker, https://github.com/mdbernard/attlesnake/issues
Platform: UNKNOWN
Classifier: Programming Language :: Python :: 3
Classifier: Programming Language :: Python :: 3.7
Classifier: Programming Language :: Python :: 3.8
Classifier: Programming Language :: Python :: 3.9
Classifier: Programming Language :: Python :: 3.10
Classifier: License :: OSI Approved :: MIT License
Classifier: Operating System :: OS Independent
Requires-Python: >=3.7
License-File: LICENSE
Requires-Dist: numpy
